forking.py
forking-0.2.dist-info/METADATA
forking-0.2.dist-info/WHEEL
forking-0.2.dist-info/top_level.txt
forking-0.2.dist-info/RECORD
