Metadata-Version: 2.4
Name: Forking
Version: 0.2
Summary: A context manager to fork.
Author-email: Julien Palard <julien@palard.fr>
License-Expression: MIT
Project-URL: homepage, https://git.afpy.org/mdk/forking
Requires-Python: >=3.9
Provides-Extra: dev
Requires-Dist: black; extra == "dev"
Requires-Dist: build; extra == "dev"
Requires-Dist: friendly-traceback; extra == "dev"
Requires-Dist: isort; extra == "dev"
Requires-Dist: mypy; extra == "dev"
Requires-Dist: pylint; extra == "dev"
Requires-Dist: pytest; extra == "dev"
Requires-Dist: ruff; extra == "dev"
Requires-Dist: tox; extra == "dev"
Requires-Dist: twine; extra == "dev"
